coqconfig/__init__.py
coqconfig/coqconfig.py
coq_config-0.0.2.dist-info/LICENSE
coq_config-0.0.2.dist-info/METADATA
coq_config-0.0.2.dist-info/WHEEL
coq_config-0.0.2.dist-info/entry_points.txt
coq_config-0.0.2.dist-info/top_level.txt
coq_config-0.0.2.dist-info/RECORD
