Metadata-Version: 2.1
Name: coq-config
Version: 0.0.2
Summary: "Script to set up a Coq project dependencies using opam, inspired by Haskell's stack."
Home-page: https://github.com/vzaliva/coq-config
Author: Vadim Zaliva
Author-email: lord@crocodile.org
License: UNKNOWN
Platform: UNKNOWN
Classifier: Environment :: Console
Classifier: License :: OSI Approved :: BSD License
Classifier: Programming Language :: Python
Classifier: Programming Language :: Python :: 3
Requires-Dist: cerberus (>=1.3.2)
Requires-Dist: click (>=7.0)
Requires-Dist: pyyaml (>=5.3.1)
